evalvia_core/__init__.py
evalvia_core/answersheet_handler.cp312-win_amd64.pyd
evalvia_core/evalvia.cp312-win_amd64.pyd
evalvia_core/llm_handler.cp312-win_amd64.pyd
evalvia_core/question_paper_handler.cp312-win_amd64.pyd
evalvia_core/datastructures/__init__.py
evalvia_core/datastructures/answersheet.py
evalvia_core/datastructures/question_paper.py
evalvia_core/datastructures/rubric.py
evalvia_core/ocr_extractor/__init__.py
evalvia_core/ocr_extractor/extractor_client.py
evalvia_core/ocr_extractor/extractor_factory.py
evalvia_core/ocr_extractor/extractor_gemini.py
evalvia_core/ocr_extractor/extractor_mathpix.py
evalvia_core/ocr_extractor/extractor_openai.py
evalvia_core/ocr_extractor/extractor_textract.py
evalvia_core/utils/__init__.py
evalvia_core/utils/json_editor.py
evalvia_core-0.1.3.dist-info/METADATA
evalvia_core-0.1.3.dist-info/WHEEL
evalvia_core-0.1.3.dist-info/top_level.txt
evalvia_core-0.1.3.dist-info/RECORD
