Metadata-Version: 2.4
Name: evalvia-core
Version: 0.1.3
Author: Rahul Dilare
Requires-Dist: mpxpy==0.0.18
Requires-Dist: pydantic_core
Requires-Dist: sniffio
Requires-Dist: anyio
Requires-Dist: openai>=1.0.0
Requires-Dist: pydantic>=2.0.0
Requires-Dist: python-dotenv>=1.0.0
Requires-Dist: boto3>=1.28.0
Requires-Dist: google-generativeai>=0.3.0
Requires-Dist: requests>=2.28.0
Requires-Dist: pillow>=9.0.0
Requires-Dist: tiktoken>=0.5.0
Requires-Dist: pymupdf
Requires-Dist: dotenv
Dynamic: author
Dynamic: requires-dist
